prrr/__init__.py
prrr/commands/init.py
prrr/commands/pr.py
prrr/main.py
prrr/utils/config_reader.py
prrr/utils/git.py
prrr-0.1.2.dist-info/METADATA
prrr-0.1.2.dist-info/WHEEL
prrr-0.1.2.dist-info/entry_points.txt
prrr-0.1.2.dist-info/RECORD
